bizstats_llm_router/__init__.py
bizstats_llm_router/base.py
bizstats_llm_router/caching.py
bizstats_llm_router/config.py
bizstats_llm_router/cost_tracking.py
bizstats_llm_router/rate_limiting.py
bizstats_llm_router/registry.py
bizstats_llm_router/router.py
bizstats_llm_router/adapters/__init__.py
bizstats_llm_router/adapters/anthropic.py
bizstats_llm_router/adapters/azure.py
bizstats_llm_router/adapters/bedrock.py
bizstats_llm_router/adapters/google.py
bizstats_llm_router/adapters/ollama.py
bizstats_llm_router/adapters/openai.py
bizstats_llm_router-0.1.0.dist-info/METADATA
bizstats_llm_router-0.1.0.dist-info/WHEEL
bizstats_llm_router-0.1.0.dist-info/RECORD
