Metadata-Version: 2.4
Name: bizstats-llm-router
Version: 0.1.0
Summary: Multi-provider LLM routing with intelligent failover, cost optimization, and CrewAI integration
Project-URL: Homepage, https://github.com/absolut-e/bizstats-llm-router
Project-URL: Documentation, https://github.com/absolut-e/bizstats-llm-router#readme
Project-URL: Repository, https://github.com/absolut-e/bizstats-llm-router
Project-URL: Issues, https://github.com/absolut-e/bizstats-llm-router/issues
Author-email: "Absolut-e Data Com Inc." <account@absolut-e.com>
License: Proprietary - Copyright (c) 2025 Absolut-e Data Com Inc. and BizStats.AI. All rights reserved.
Keywords: ai,anthropic,azure,bedrock,crewai,failover,google,llm,machine-learning,multi-provider,ollama,openai,routing
Classifier: Development Status :: 4 - Beta
Classifier: Framework :: AsyncIO
Classifier: Intended Audience :: Developers
Classifier: License :: Other/Proprietary License
Classifier: Operating System :: OS Independent
Classifier: Programming Language :: Python :: 3
Classifier: Programming Language :: Python :: 3.11
Classifier: Programming Language :: Python :: 3.12
Classifier: Topic :: Scientific/Engineering :: Artificial Intelligence
Classifier: Topic :: Software Development :: Libraries :: Python Modules
Classifier: Typing :: Typed
Requires-Python: >=3.11
Requires-Dist: aiohttp>=3.9.0
Requires-Dist: httpx>=0.26.0
Requires-Dist: pydantic-settings>=2.0.0
Requires-Dist: pydantic>=2.0.0
Requires-Dist: tenacity>=8.2.0
Provides-Extra: all
Requires-Dist: anthropic>=0.18.0; extra == 'all'
Requires-Dist: crewai>=0.186.0; extra == 'all'
Requires-Dist: google-generativeai>=0.4.0; extra == 'all'
Requires-Dist: litellm>=1.0.0; extra == 'all'
Requires-Dist: ollama>=0.1.0; extra == 'all'
Requires-Dist: openai>=1.0.0; extra == 'all'
Requires-Dist: redis>=5.0.0; extra == 'all'
Provides-Extra: anthropic
Requires-Dist: anthropic>=0.18.0; extra == 'anthropic'
Provides-Extra: crewai
Requires-Dist: crewai>=0.186.0; extra == 'crewai'
Requires-Dist: litellm>=1.0.0; extra == 'crewai'
Provides-Extra: dev
Requires-Dist: black>=24.0.0; extra == 'dev'
Requires-Dist: mypy>=1.8.0; extra == 'dev'
Requires-Dist: pytest-asyncio>=0.23.0; extra == 'dev'
Requires-Dist: pytest-cov>=4.1.0; extra == 'dev'
Requires-Dist: pytest-mock>=3.12.0; extra == 'dev'
Requires-Dist: pytest>=8.0.0; extra == 'dev'
Requires-Dist: ruff>=0.1.0; extra == 'dev'
Provides-Extra: google
Requires-Dist: google-generativeai>=0.4.0; extra == 'google'
Provides-Extra: ollama
Requires-Dist: ollama>=0.1.0; extra == 'ollama'
Provides-Extra: openai
Requires-Dist: openai>=1.0.0; extra == 'openai'
Provides-Extra: redis
Requires-Dist: redis>=5.0.0; extra == 'redis'
Provides-Extra: test
Requires-Dist: aioresponses>=0.7.0; extra == 'test'
Requires-Dist: pytest-asyncio>=0.23.0; extra == 'test'
Requires-Dist: pytest-cov>=4.1.0; extra == 'test'
Requires-Dist: pytest-mock>=3.12.0; extra == 'test'
Requires-Dist: pytest>=8.0.0; extra == 'test'
Requires-Dist: respx>=0.20.0; extra == 'test'
